django_debug_toolbar_assistant_panel/__init__.py
django_debug_toolbar_assistant_panel/apps.py
django_debug_toolbar_assistant_panel/panel.py
django_debug_toolbar_assistant_panel/urls.py
django_debug_toolbar_assistant_panel/views.py
django_debug_toolbar_assistant_panel/static/__debug__/djdt_assistant_panel/css/panel.css
django_debug_toolbar_assistant_panel/static/__debug__/djdt_assistant_panel/js/panel.js
django_debug_toolbar_assistant_panel/templates/panels/djdt_assistant.html
django_debug_toolbar_assistant_panel-0.1.0.dist-info/METADATA
django_debug_toolbar_assistant_panel-0.1.0.dist-info/WHEEL
django_debug_toolbar_assistant_panel-0.1.0.dist-info/top_level.txt
django_debug_toolbar_assistant_panel-0.1.0.dist-info/RECORD
